ez_pipe/__init__.py
ez_pipe/main.py
ezpipe-0.0.1.dist-info/LICENSE
ezpipe-0.0.1.dist-info/METADATA
ezpipe-0.0.1.dist-info/WHEEL
ezpipe-0.0.1.dist-info/top_level.txt
ezpipe-0.0.1.dist-info/RECORD
